imaxt_mosaic/__init__.py
imaxt_mosaic/calibration.py
imaxt_mosaic/raw.py
imaxt_mosaic/settings.py
imaxt_mosaic/stagepos.py
imaxt_mosaic/stitcher.py
imaxt_mosaic/tileset.py
imaxt_mosaic/typing_utils.py
imaxt_mosaic/utils.py
imaxt_mosaic/bead_detect/__init__.py
imaxt_mosaic/bead_detect/bead_detector.py
imaxt_mosaic/bead_detect/runner.py
imaxt_mosaic/beadlib/__init__.py
imaxt_mosaic/beadlib/detect.py
imaxt_mosaic/owl/__init__.py
imaxt_mosaic/owl/main.py
imaxt_mosaic/owl/schema.py
imaxt_mosaic/plugins/__init__.py
imaxt_mosaic/plugins/axio.py
imaxt_mosaic/plugins/stpt.py
imaxt_mosaic/stitchlib/__init__.py
imaxt_mosaic/stitchlib/metrics.py
imaxt_mosaic/stitchlib/mutual_information.py
imaxt_mosaic/stitchlib/optimization.py
imaxt_mosaic/stitchlib/refinement.py
imaxt_mosaic/stitchlib/stage_model.py
imaxt_mosaic/stitchlib/translation.py
imaxt_mosaic-1.15.0.dist-info/LICENSE
imaxt_mosaic-1.15.0.dist-info/METADATA
imaxt_mosaic-1.15.0.dist-info/WHEEL
imaxt_mosaic-1.15.0.dist-info/entry_points.txt
imaxt_mosaic-1.15.0.dist-info/top_level.txt
imaxt_mosaic-1.15.0.dist-info/RECORD
