Metadata-Version: 2.1
Name: imaxt-mosaic
Version: 1.15.0
Summary: Image stitching
Home-page: https://gitlab.developers.cam.ac.uk/astronomy/camcead/imaxt/imaxt-mosaic-pipeline
Author: attr: imaxt_mosaic.__author__
Author-email: "E.GonzalezSolares@ast.cam.ac.uk"
Project-URL: Bug Tracker, https://gitlab.developers.cam.ac.uk/astronomy/camcead/imaxt/imaxt-mosaic-pipeline/-/issues
Classifier: Development Status :: 4 - Beta
Classifier: Programming Language :: Python
Classifier: Programming Language :: Python :: 3
Classifier: Programming Language :: Python :: 3.7
Classifier: Programming Language :: Python :: 3.8
Classifier: Programming Language :: Python :: 3.9
Classifier: Programming Language :: Python :: 3.10
Classifier: License :: OSI Approved :: MIT License
Classifier: Operating System :: OS Independent
Requires-Python: >=3.7
License-File: LICENSE
Requires-Dist: astropy (==5.1.1)
Requires-Dist: blosc (==1.10.6)
Requires-Dist: numpy (==1.22.4)
Requires-Dist: pandas (==1.4.2)
Requires-Dist: opencv-python-headless (==4.6.0.66)
Requires-Dist: owl-pipeline-develop
Requires-Dist: dask
Requires-Dist: distributed
Requires-Dist: imageio (==2.19.3)
Requires-Dist: lz4 (==4.0.1)
Requires-Dist: networkx (==2.8.3)
Requires-Dist: pyarrow (==8.0.0)
Requires-Dist: scikit-image (==0.19.2)
Requires-Dist: scikit-learn (==1.1.1)
Requires-Dist: sep (==1.2.1)
Requires-Dist: shapely (==1.8.2)
Requires-Dist: voluptuous
Requires-Dist: xarray (==2022.6.0)
Requires-Dist: zarr (==2.11.3)
Requires-Dist: stpt2zarr (>=0.1.6)
Requires-Dist: axio2zarr (>=0.2.4)
